gc3libs/__init__.py
gc3libs/cmdline.py
gc3libs/config.py
gc3libs/core.py
gc3libs/debug.py
gc3libs/defaults.py
gc3libs/events.py
gc3libs/exceptions.py
gc3libs/poller.py
gc3libs/quantity.py
gc3libs/session.py
gc3libs/template.py
gc3libs/url.py
gc3libs/utils.py
gc3libs/workflow.py
gc3libs/application/__init__.py
gc3libs/application/apppot.py
gc3libs/application/codeml.py
gc3libs/application/demo.py
gc3libs/application/gamess.py
gc3libs/application/rosetta.py
gc3libs/application/turbomole.py
gc3libs/authentication/__init__.py
gc3libs/authentication/ec2.py
gc3libs/authentication/openstack.py
gc3libs/authentication/ssh.py
gc3libs/backends/__init__.py
gc3libs/backends/_cloud.py
gc3libs/backends/batch.py
gc3libs/backends/ec2.py
gc3libs/backends/lsf.py
gc3libs/backends/noop.py
gc3libs/backends/openstack.py
gc3libs/backends/pbs.py
gc3libs/backends/sge.py
gc3libs/backends/shellcmd.py
gc3libs/backends/slurm.py
gc3libs/backends/transport.py
gc3libs/backends/vmpool.py
gc3libs/compat/__init__.py
gc3libs/compat/_collections.py
gc3libs/compat/_functools.py
gc3libs/compat/_inspect.py
gc3libs/compat/toposort.py
gc3libs/etc/codeml.pl
gc3libs/etc/gbenchmark_infomap_wrapper.sh
gc3libs/etc/gbenchmark_wrapper.sh
gc3libs/etc/gbenchmark_wrapper_allinone.py
gc3libs/etc/gc3pie.conf.example
gc3libs/etc/gcelljunction_wrapper.sh
gc3libs/etc/geosphere_wrapper.sh
gc3libs/etc/geotop_wrap.sh
gc3libs/etc/gmodis_wrapper.sh
gc3libs/etc/gndn_wrapper.sh
gc3libs/etc/gnfs-cmd
gc3libs/etc/gnlp_wrapper.py
gc3libs/etc/gpyrad_wrapper.sh
gc3libs/etc/grdock_wrapper.sh
gc3libs/etc/gstructure_wrapper.sh
gc3libs/etc/gweight_wrap.sh
gc3libs/etc/gwrappermc_wrapper.sh
gc3libs/etc/logging.conf.example
gc3libs/etc/rosetta.sh
gc3libs/etc/run_R.sh
gc3libs/etc/run_gtsub_control.sh
gc3libs/etc/run_matlab.sh
gc3libs/etc/smd_projections_wrapper.sh
gc3libs/etc/square.sh
gc3libs/etc/turbomole.sh
gc3libs/optimizer/__init__.py
gc3libs/optimizer/dif_evolution.py
gc3libs/optimizer/drivers.py
gc3libs/optimizer/extra.py
gc3pie-2.6.8.dist-info/LICENSE.md
gc3pie-2.6.8.dist-info/METADATA
gc3pie-2.6.8.dist-info/WHEEL
gc3pie-2.6.8.dist-info/entry_points.txt
gc3pie-2.6.8.dist-info/pbr.json
gc3pie-2.6.8.dist-info/top_level.txt
gc3pie-2.6.8.dist-info/zip-safe
gc3pie-2.6.8.dist-info/RECORD
