Metadata-Version: 2.1
Name: gc3pie
Version: 2.6.8
Summary: A Python library and simple command-line frontend for computational job submission to multiple resources.
Home-page: http://gc3pie.readthedocs.io/
Author: Sergio Maffioletti, Antonio Messina, Riccardo Murri
Author-email: gc3pie-dev@googlegroups.com
License: LGPL
Keywords: batch cloud cluster differential optimization ec2 gridengine job management large-scale data analysis openstack pbs remote execution sge slurm ssh torque workflow
Platform: UNKNOWN
Classifier: Development Status :: 5 - Production/Stable
Classifier: Environment :: Console
Classifier: Intended Audience :: Developers
Classifier: Intended Audience :: Science/Research
Classifier: License :: OSI Approved :: GNU Library or Lesser General Public License (LGPL)
Classifier: License :: DFSG approved
Classifier: Operating System :: POSIX :: Linux
Classifier: Programming Language :: Python
Classifier: Programming Language :: Python :: 2
Classifier: Programming Language :: Python :: 2.6
Classifier: Programming Language :: Python :: 2.7
Classifier: Programming Language :: Python :: 3
Classifier: Programming Language :: Python :: 3.5
Classifier: Programming Language :: Python :: 3.6
Classifier: Programming Language :: Python :: 3.7
Classifier: Programming Language :: Python :: 3.8
Classifier: Programming Language :: Python :: 3.9
Classifier: Topic :: Scientific/Engineering
Classifier: Topic :: Scientific/Engineering :: Bio-Informatics
Classifier: Topic :: Scientific/Engineering :: Chemistry
Classifier: Topic :: System :: Distributed Computing
Requires-Dist: blinker
Requires-Dist: coloredlogs
Requires-Dist: dictproxyhack
Requires-Dist: future (>=0.17.0)
Requires-Dist: lockfile
Requires-Dist: paramiko
Requires-Dist: parsedatetime
Requires-Dist: prettytable
Requires-Dist: pyCLI
Requires-Dist: pycrypto
Requires-Dist: python-daemon
Requires-Dist: pyyaml
Requires-Dist: six
Requires-Dist: sqlalchemy
Provides-Extra: daemon
Requires-Dist: inotify-simple ; extra == 'daemon'
Provides-Extra: ec2
Requires-Dist: boto ; extra == 'ec2'
Provides-Extra: openstack
Requires-Dist: os-client-config ; extra == 'openstack'
Requires-Dist: python-glanceclient ; extra == 'openstack'
Requires-Dist: python-keystoneclient ; extra == 'openstack'
Requires-Dist: python-neutronclient ; extra == 'openstack'
Requires-Dist: python-novaclient ; extra == 'openstack'
Requires-Dist: python-swiftclient ; extra == 'openstack'
Provides-Extra: optimizer
Requires-Dist: numpy ; extra == 'optimizer'
